framework/__init__.py
framework/Utils/__init__.py
framework/Utils/create_general_directory.py
framework/Utils/exception_handling.py
framework/Utils/static_methods.py
framework/Utils/utils.py
framework/config/__init__.py
framework/config/mobile_config.py
framework/core/__init__.py
framework/core/actions_enums.py
framework/core/base_page.py
framework/pages/__init__.py
framework/pages/allure_page.py
framework/pages/assertions_page.py
framework/pages/database_connection_page.py
framework/pages/logging_page.py
complete_automation_framework-1.0.0.dist-info/METADATA
complete_automation_framework-1.0.0.dist-info/WHEEL
complete_automation_framework-1.0.0.dist-info/top_level.txt
complete_automation_framework-1.0.0.dist-info/RECORD
